dbt_gen/__init__.py
dbt_gen/cli.py
dbt_gen/generate_base_model.py
dbt_gen/generate_base_test.py
dbt_gen/generate_dbt.py
dbt_gen/generate_source_yaml.py
dbt_gen/get_template.py
dbt_gen/runner.py
dbt_gen/templater.py
dbt_gen/utils.py
dbt_gen/adapters/__init__.py
dbt_gen/adapters/base.py
dbt_gen/adapters/bigquery_adapter.py
dbt_gen/adapters/snowflake_adapter.py
dbt_gen/templates/__init__.py
dbt_gen/templates/base_model.sql
dbt_gen/templates/base_tests.yml
dbt_gen-0.1.7.dist-info/LICENSE.md
dbt_gen-0.1.7.dist-info/METADATA
dbt_gen-0.1.7.dist-info/WHEEL
dbt_gen-0.1.7.dist-info/entry_points.txt
dbt_gen-0.1.7.dist-info/top_level.txt
dbt_gen-0.1.7.dist-info/RECORD
