Metadata-Version: 2.1
Name: dbt-gen
Version: 0.1.7
Summary: Tool to generate dbt resources.
Home-page: https://github.com/joon-solutions/dbt-gen
Author: Joon Solutions
Author-email: tien.tq@joonsolutions.com
License: GPLv3
Platform: UNKNOWN
Requires-Dist: cookiecutter (==1.7.3)
Requires-Dist: google-cloud-bigquery (>=2.34.0)
Requires-Dist: jinja2 (>=2.11.3)
Requires-Dist: pandas (>=1.3.4)
Requires-Dist: pyarrow (<6.1.0,>=6.0.0)
Requires-Dist: pyYAML (>=6.0)
Requires-Dist: snowflake-connector-python (>=2.7.4)
Requires-Dist: tqdm (>=4.63.0)
Provides-Extra: tests
Requires-Dist: black (==22.1.0) ; extra == 'tests'
Requires-Dist: flake8 (==4.0.1) ; extra == 'tests'
Requires-Dist: pytest (==7.0.1) ; extra == 'tests'
